{
  "rows": [
    {
      "haksu_cd": "AS287",
      "sigan": "화 6 7 8",
      "gwamok_kname": "특허와기술개발",
      "hakjum": 3,
      "prof_name": "박찬정",
      "params": "01@0476@00000",
      "isu_name": "과학",
      "abeek": "Y",
      "gwamok_no": "0476",
      "haknyun": " ",
      "rowid": 1,
      "gyoyuk_gwajung_gb": "01",
      "jojik_gb": "A1000"
    },
    {
      "haksu_cd": "AS287",
      "sigan": "수 1 2 3",
      "gwamok_kname": "특허와기술개발",
      "hakjum": 3,
      "prof_name": "박찬정",
      "params": "01@0477@00000",
      "isu_name": "과학",
      "abeek": "Y",
      "gwamok_no": "0477",
      "haknyun": " ",
      "rowid": 2,
      "gyoyuk_gwajung_gb": "01",
      "jojik_gb": "A1000"
    },
    {
      "haksu_cd": "AS287",
      "sigan": "수 6 7 8",
      "gwamok_kname": "특허와기술개발",
      "hakjum": 3,
      "prof_name": "박찬정",
      "params": "01@0478@00000",
      "isu_name": "과학",
      "abeek": "Y",
      "gwamok_no": "0478",
      "haknyun": " ",
      "rowid": 3,
      "gyoyuk_gwajung_gb": "01",
      "jojik_gb": "A1000"
    },
    {
      "haksu_cd": "AS287",
      "sigan": "목 1 2 3",
      "gwamok_kname": "특허와기술개발",
      "hakjum": 3,
      "prof_name": "박찬정",
      "params": "01@0479@00000",
      "isu_name": "과학",
      "abeek": "Y",
      "gwamok_no": "0479",
      "haknyun": " ",
      "rowid": 4,
      "gyoyuk_gwajung_gb": "01",
      "jojik_gb": "A1000"
    },
    {
      "haksu_cd": "AS287",
      "sigan": "목 6 7 8",
      "gwamok_kname": "특허와기술개발",
      "hakjum": 3,
      "prof_name": "박찬정",
      "params": "01@0480@00000",
      "isu_name": "과학",
      "abeek": "Y",
      "gwamok_no": "0480",
      "haknyun": " ",
      "rowid": 5,
      "gyoyuk_gwajung_gb": "01",
      "jojik_gb": "A1000"
    }
  ]
}
